[
  {
    "version": "model-v1.0.1",
    "title": "model-v1.0.1",
    "aliases": [
      "latest"
    ]
  },
  {
    "version": "model-v0.0.5",
    "title": "model-v0.0.5",
    "aliases": []
  },
  {
    "version": "model-v0.0.4",
    "title": "model-v0.0.4",
    "aliases": []
  },
  {
    "version": "model-v0.0.3",
    "title": "model-v0.0.3",
    "aliases": []
  },
  {
    "version": "v0.2.12",
    "title": "v0.2.12",
    "aliases": []
  },
  {
    "version": "v0.2.11",
    "title": "v0.2.11",
    "aliases": []
  },
  {
    "version": "v0.2.10",
    "title": "v0.2.10",
    "aliases": []
  },
  {
    "version": "v0.2.9",
    "title": "v0.2.9",
    "aliases": []
  }
]
